pysesame3/__init__.py
pysesame3/auth.py
pysesame3/chsesame2.py
pysesame3/chsesamebot.py
pysesame3/cloud.py
pysesame3/const.py
pysesame3/device.py
pysesame3/helper.py
pysesame3/history.py
pysesame3/lock.py
pysesame3-0.6.0.dist-info/LICENSE
pysesame3-0.6.0.dist-info/WHEEL
pysesame3-0.6.0.dist-info/METADATA
pysesame3-0.6.0.dist-info/RECORD
