Metadata-Version: 2.1
Name: pysesame3
Version: 0.6.0
Summary: Unofficial library to communicate with Sesame smart locks.
Home-page: https://github.com/mochipon/pysesame3
License: MIT
Author: Masaki Tagawa
Author-email: masaki@tagawa.email
Requires-Python: >=3.7,<4.0
Classifier: Development Status :: 4 - Beta
Classifier: Intended Audience :: Developers
Classifier: License :: OSI Approved :: MIT License
Classifier: Natural Language :: English
Classifier: Programming Language :: Python :: 3
Classifier: Programming Language :: Python :: 3.10
Classifier: Programming Language :: Python :: 3.7
Classifier: Programming Language :: Python :: 3.8
Classifier: Programming Language :: Python :: 3.9
Provides-Extra: cognito
Provides-Extra: doc
Requires-Dist: awsiotsdk (>=1.11.1,<2.0.0); extra == "cognito"
Requires-Dist: boto3 (>=1.23.6,<2.0.0); extra == "cognito"
Requires-Dist: certifi; extra == "cognito"
Requires-Dist: importlib-metadata (>=4.11.4,<5.0.0); python_version < "3.8"
Requires-Dist: livereload (>=2.6.3,<3.0.0); extra == "doc"
Requires-Dist: mkdocs (>=1.3.0,<2.0.0); extra == "doc"
Requires-Dist: mkdocs-autorefs (>=0.4.1,<0.5.0); extra == "doc"
Requires-Dist: mkdocs-include-markdown-plugin (>=3.5.0,<4.0.0); extra == "doc"
Requires-Dist: mkdocs-material (>=8.2.15,<9.0.0); extra == "doc"
Requires-Dist: mkdocstrings (>=0.19.0,<0.20.0); extra == "doc"
Requires-Dist: mkdocstrings-python (>=0.7.0,<0.8.0); extra == "doc"
Requires-Dist: pycryptodome (>=3.14.1,<4.0.0)
Requires-Dist: requests (>=2.27.1,<3.0.0)
Requires-Dist: requests-aws4auth (>=1.1.2,<2.0.0); extra == "cognito"
Requires-Dist: typing-extensions (>=4.2.0,<5.0.0); python_version < "3.8"
